dynamo_dlm-2.1.0.dist-info/METADATA
dynamo_dlm-2.1.0.dist-info/WHEEL
dynamo_dlm-2.1.0.dist-info/entry_points.txt
dynamo_dlm-2.1.0.dist-info/licenses/LICENSE
dynamo_dlm/__init__.py
dynamo_dlm/lock.py
dynamo_dlm-2.1.0.dist-info/RECORD
