Metadata-Version: 2.4
Name: dynamo-dlm
Version: 2.1.0
Summary: Distributed lock manager for Python using AWS DynamoDB for persistence
Author-Email: Barry Barrette <barrybarrette@gmail.com>
License-Expression: GPL-3.0-or-later
Project-URL: Homepage, https://github.com/whitebarry/dynamo-dlm
Requires-Python: >=3.9
Requires-Dist: backoff>=1.10.0
Requires-Dist: boto3>=1.14.12
